em_driver/Database.py
em_driver/__init__.py
em_driver-0.0.4.dist-info/LICENSE
em_driver-0.0.4.dist-info/METADATA
em_driver-0.0.4.dist-info/WHEEL
em_driver-0.0.4.dist-info/top_level.txt
em_driver-0.0.4.dist-info/RECORD
